smup/__init__.py
smup/smup.py
tests/__init__.py
tests/test_smup.py
smup-0.2.2.dist-info/AUTHORS.rst
smup-0.2.2.dist-info/LICENSE
smup-0.2.2.dist-info/METADATA
smup-0.2.2.dist-info/WHEEL
smup-0.2.2.dist-info/top_level.txt
smup-0.2.2.dist-info/RECORD
