Metadata-Version: 2.1
Name: smup
Version: 0.2.2
Summary: Stable Matching is a powerful theory that can make a lot of useful stuff. SMUP uses it to make useless, but sometimes nice, random pictures.
Home-page: https://github.com/balouf/smup
Author: Fabien Mathieu
Author-email: fabien.mathieu@normalesup.org
License: GNU General Public License v3
Keywords: smup
Platform: UNKNOWN
Classifier: Development Status :: 2 - Pre-Alpha
Classifier: Intended Audience :: Developers
Classifier: License :: OSI Approved :: GNU General Public License v3 (GPLv3)
Classifier: Natural Language :: English
Classifier: Programming Language :: Python :: 3
Classifier: Programming Language :: Python :: 3.6
Classifier: Programming Language :: Python :: 3.7
Classifier: Programming Language :: Python :: 3.8
Classifier: Programming Language :: Python :: 3.9
Requires-Python: >=3.6
Requires-Dist: numpy
Requires-Dist: numba
Requires-Dist: matplotlib
